raspi_music_button/__init__.py
raspi_music_button/bootstrap.py
raspi_music_button/adapters/__init__.py
raspi_music_button/adapters/amixer.py
raspi_music_button/adapters/aplay.py
raspi_music_button/adapters/mpg321.py
raspi_music_button/domain/__init__.py
raspi_music_button/domain/model/__init__.py
raspi_music_button/entrypoints/__init__.py
raspi_music_button/entrypoints/cli/__init__.py
raspi_music_button/entrypoints/cli/button.py
raspi_music_button/entrypoints/cli/play.py
raspi_music_button/entrypoints/cli/utils/__init__.py
raspi_music_button/entrypoints/cli/utils/option.py
raspi_music_button/services/__init__.py
raspi_music_button/services/service.py
raspi_music_button-0.1.0.dist-info/LICENSE
raspi_music_button-0.1.0.dist-info/METADATA
raspi_music_button-0.1.0.dist-info/WHEEL
raspi_music_button-0.1.0.dist-info/entry_points.txt
raspi_music_button-0.1.0.dist-info/top_level.txt
raspi_music_button-0.1.0.dist-info/RECORD
