Metadata-Version: 2.1
Name: raspi-music-button
Version: 0.1.0
Summary: A simple package for Raspberry Pi to play music and trigger music by buttons over the gpio.
Home-page: https://github.com/pschleiter/raspi_music_button
Author: Patrick Schleiter
License: MIT License
Platform: UNKNOWN
Classifier: Operating System :: POSIX :: Linux
Classifier: Programming Language :: Python
Requires-Python: >=3.8
License-File: LICENSE
Requires-Dist: click (>=8.1.2<9)
Requires-Dist: gpiozero (>=1.6.2<2)
